<?xml version="1.0" encoding="UTF-8"?>
<node>
<version>6</version>
<dict>
  <key>duplicate_of</key><string>29cf95a2-0215-47ed-87a6-8a6d828613d6</string>
  <key>title</key><string>nbtscan</string>
  <key>nodeid</key><string>4d98005e-2797-4f65-b032-d29fab6d57f6</string>
  <key>modified_time</key><integer>1565811063</integer>
  <key>expanded2</key><true/>
  <key>version</key><integer>6</integer>
  <key>content_type</key><string>text/xhtml+xml</string>
  <key>created_time</key><integer>1565811023</integer>
  <key>order</key><integer>5</integer>
</dict>
</node>
